netutil/__init__.py
netutil-0.0.7.dist-info/LICENSE
netutil-0.0.7.dist-info/METADATA
netutil-0.0.7.dist-info/WHEEL
netutil-0.0.7.dist-info/top_level.txt
netutil-0.0.7.dist-info/RECORD
