Metadata-Version: 2.1
Name: netutil
Version: 0.0.7
Summary: Simplified way to get networking port status
Home-page: https://github.com/cjerrington/netutils
Author: Clayton Errington
Author-email: me@claytonerrington.com
License: UNKNOWN
Platform: UNKNOWN
Classifier: Programming Language :: Python :: 3
Classifier: License :: OSI Approved :: MIT License
Classifier: Operating System :: OS Independent
Requires-Python: >=3.6
